<?xml version="1.0" encoding="UTF-8"?>
<vcs-root xmlns:xsi="http://www.w3.org/2001/XMLSchema-instance" uuid="71fc8507-c9e2-4885-bbaf-de7ab60c2af0" type="jetbrains.git" xsi:noNamespaceSchemaLocation="https://www.jetbrains.com/teamcity/schemas/2021.1/project-config.xsd">
  <name>https://github.com/rayhive/anewtodolist.git#refs/heads/main</name>
  <param name="agentCleanFilesPolicy" value="ALL_UNTRACKED" />
  <param name="agentCleanPolicy" value="ON_BRANCH_CHANGE" />
  <param name="authMethod" value="PASSWORD" />
  <param name="branch" value="refs/heads/main" />
  <param name="ignoreKnownHosts" value="true" />
  <param name="secure:password" value="credentialsJSON:63032079-9df5-44e8-8255-0cc6ee95780d" />
  <param name="submoduleCheckout" value="CHECKOUT" />
  <param name="teamcity:branchSpec" value="refs/heads/*" />
  <param name="url" value="https://github.com/rayhive/anewtodolist.git" />
  <param name="useAlternates" value="AUTO" />
  <param name="usernameStyle" value="USERID" />
</vcs-root>

